pibooth_google_photo.py
pibooth_google_photo-1.2.3.dist-info/LICENSE
pibooth_google_photo-1.2.3.dist-info/METADATA
pibooth_google_photo-1.2.3.dist-info/WHEEL
pibooth_google_photo-1.2.3.dist-info/entry_points.txt
pibooth_google_photo-1.2.3.dist-info/top_level.txt
pibooth_google_photo-1.2.3.dist-info/RECORD
